itk/_DissolvePython.abi3.so
itk/DissolvePython.py
itk/itkDissolveMaskImageFilterPython.py
itk/Configuration/DissolveConfig.py
itk/Configuration/Dissolve_snake_case.py
itk_dissolve-1.0.7.dist-info/RECORD
itk_dissolve-1.0.7.dist-info/entry_points.txt
itk_dissolve-1.0.7.dist-info/WHEEL
itk_dissolve-1.0.7.dist-info/METADATA
itk_dissolve-1.0.7.dist-info/licenses/LICENSE
itk_dissolve.libs/libtbb-3c88584c.so.12.9
