Metadata-Version: 2.1
Name: itk-dissolve
Version: 1.0.7
Summary: This is a module for the Insight Toolkit (ITK) that provides filters to replace regions within a masked region with the surrounding labels.
Keywords: itk
Author-Email: Bryn Lloyd <lloyd@itis.swiss>
License: MIT License
Classifier: Development Status :: 4 - Beta
Classifier: Intended Audience :: Developers
Classifier: Intended Audience :: Education
Classifier: Intended Audience :: Healthcare Industry
Classifier: Intended Audience :: Science/Research
Classifier: License :: OSI Approved :: Apache Software License
Classifier: Operating System :: Android
Classifier: Operating System :: MacOS
Classifier: Operating System :: Microsoft :: Windows
Classifier: Operating System :: POSIX
Classifier: Operating System :: Unix
Classifier: Programming Language :: C++
Classifier: Programming Language :: Python
Classifier: Topic :: Scientific/Engineering
Classifier: Topic :: Scientific/Engineering :: Information Analysis
Classifier: Topic :: Scientific/Engineering :: Medical Science Apps.
Classifier: Topic :: Software Development :: Libraries
Project-URL: Download, https://github.com/dyollb/ITKDissolve
Project-URL: Homepage, https://github.com/dyollb/ITKDissolve
Requires-Python: >=3.8
Requires-Dist: itk==5.4.*
